Verilator_Tests/spi/top.v
module top (
    input wire clk_25mhz,

    output reg spi_clk = 0,

    output reg spi_mosi = 0,
    input reg spi_miso = 0,

    output wire spi_cs
);

assign spi_cs = 0;  // Always selected (for test)

reg [7:0] mosi_shift = 8'b01101011;  // Example byte
reg [3:0] bit_counter = 0;
reg spi_clk_en = 0;

always_ff @(posedge clk_25mhz) begin
    spi_clk <= ~spi_clk;

    if (spi_clk == 0) begin
        // Falling edge: shift data
        spi_mosi <= mosi_shift[7];
        mosi_shift <= {mosi_shift[6:0], 1'b0};
        bit_counter <= bit_counter + 1;
    end
end

endmodule

Verilator_Tests/spi/wave.vcd
$version Generated by VerilatedVcd $end
$timescale 1ps $end
 $scope module TOP $end
  $var wire 1 # clk_25mhz $end
  $var wire 1 $ spi_clk $end
  $var wire 1 % spi_mosi $end
  $var wire 1 & spi_miso $end
  $var wire 1 ' spi_cs $end
  $scope module top $end
   $var wire 1 # clk_25mhz $end
   $var wire 1 $ spi_clk $end
   $var wire 1 % spi_mosi $end
   $var wire 1 & spi_miso $end
   $var wire 1 ' spi_cs $end
   $var wire 8 ( mosi_shift [7:0] $end
   $var wire 4 ) bit_counter [3:0] $end
   $var wire 1 * spi_clk_en $end
  $upscope $end
 $upscope $end
$enddefinitions $end


#0
1#
0$
0%
0&
0'
b01101011 (
b0000 )
0*
#20
0#
#40
1#
1$
b11010110 (
b0001 )
#60
0#
#80
1#
0$
#100
0#
#120
1#
1$
1%
b10101100 (
b0010 )
#140
0#
#160
1#
0$
#180
0#
#200
1#
1$
b01011000 (
b0011 )
#220
0#
#240
1#
0$
#260
0#
#280
1#
1$
0%
b10110000 (
b0100 )
#300
0#
#320
1#
0$
#340
0#
#360
1#
1$
1%
b01100000 (
b0101 )
#380
0#
#400
1#
0$
#420
0#
#440
1#
1$
0%
b11000000 (
b0110 )
#460
0#
#480
1#
0$
#500
0#
#520
1#
1$
1%
b10000000 (
b0111 )
#540
0#
#560
1#
0$
#580
0#
#600
1#
1$
b00000000 (
b1000 )
#620
0#
#640
1#
0$
#660
0#
#680
1#
1$
0%
b1001 )
#700
0#
#720
1#
0$
#740
0#
#760
1#
1$
b1010 )
#780
0#
#800
1#
0$
#820
0#
#840
1#
1$
b1011 )
#860
0#
#880
1#
0$
#900
0#
#920
1#
1$
b1100 )
#940
0#
#960
1#
0$
#980
0#
#1000
1#
1$
b1101 )
#1020
0#
#1040
1#
0$
#1060
0#
#1080
1#
1$
b1110 )
#1100
0#
#1120
1#
0$
#1140
0#
#1160
1#
1$
b1111 )
#1180
0#
#1200
1#
0$
#1220
0#
#1240
1#
1$
b0000 )
#1260
0#
#1280
1#
0$
#1300
0#
#1320
1#
1$
b0001 )
#1340
0#
#1360
1#
0$
#1380
0#
#1400
1#
1$
b0010 )
#1420
0#
#1440
1#
0$
#1460
0#
#1480
1#
1$
b0011 )
#1500
0#
#1520
1#
0$
#1540
0#
#1560
1#
1$
b0100 )
#1580
0#
#1600
1#
0$
#1620
0#
#1640
1#
1$
b0101 )
#1660
0#
#1680
1#
0$
#1700
0#
#1720
1#
1$
b0110 )
#1740
0#
#1760
1#
0$
#1780
0#
#1800
1#
1$
b0111 )
#1820
0#
#1840
1#
0$
#1860
0#
#1880
1#
1$
b1000 )
#1900
0#
#1920
1#
0$
#1940
0#
#1960
1#
1$
b1001 )
#1980
0#
#2000
1#
0$
#2020
0#
#2040
1#
1$
b1010 )
#2060
0#
#2080
1#
0$
#2100
0#
#2120
1#
1$
b1011 )
#2140
0#
#2160
1#
0$
#2180
0#
#2200
1#
1$
b1100 )
#2220
0#
#2240
1#
0$
#2260
0#
#2280
1#
1$
b1101 )
#2300
0#
#2320
1#
0$
#2340
0#
#2360
1#
1$
b1110 )
#2380
0#
#2400
1#
0$
#2420
0#
#2440
1#
1$
b1111 )
#2460
0#
#2480
1#
0$
#2500
0#
#2520
1#
1$
b0000 )
#2540
0#
#2560
1#
0$
#2580
0#
#2600
1#
1$
b0001 )
#2620
0#
#2640
1#
0$
#2660
0#
#2680
1#
1$
b0010 )
#2700
0#
#2720
1#
0$
#2740
0#
#2760
1#
1$
b0011 )
#2780
0#
#2800
1#
0$
#2820
0#
#2840
1#
1$
b0100 )
#2860
0#
#2880
1#
0$
#2900
0#
#2920
1#
1$
b0101 )
#2940
0#
#2960
1#
0$
#2980
0#
#3000
1#
1$
b0110 )
#3020
0#
#3040
1#
0$
#3060
0#
#3080
1#
1$
b0111 )
#3100
0#
#3120
1#
0$
#3140
0#
#3160
1#
1$
b1000 )
#3180
0#
#3200
1#
0$
#3220
0#
#3240
1#
1$
b1001 )
#3260
0#
#3280
1#
0$
#3300
0#
#3320
1#
1$
b1010 )
#3340
0#
#3360
1#
0$
#3380
0#
#3400
1#
1$
b1011 )
#3420
0#
#3440
1#
0$
#3460
0#
#3480
1#
1$
b1100 )
#3500
0#
#3520
1#
0$
#3540
0#
#3560
1#
1$
b1101 )
#3580
0#
#3600
1#
0$
#3620
0#
#3640
1#
1$
b1110 )
#3660
0#
#3680
1#
0$
#3700
0#
#3720
1#
1$
b1111 )
#3740
0#
#3760
1#
0$
#3780
0#
#3800
1#
1$
b0000 )
#3820
0#
#3840
1#
0$
#3860
0#
#3880
1#
1$
b0001 )
#3900
0#
#3920
1#
0$
#3940
0#
#3960
1#
1$
b0010 )
#3980
0#
#4000
1#
0$
#4020
0#
#4040
1#
1$
b0011 )
#4060
0#
#4080
1#
0$
#4100
0#
#4120
1#
1$
b0100 )
#4140
0#
#4160
1#
0$
#4180
0#
#4200
1#
1$
b0101 )
#4220
0#
#4240
1#
0$
#4260
0#
#4280
1#
1$
b0110 )
#4300
0#
#4320
1#
0$
#4340
0#
#4360
1#
1$
b0111 )
#4380
0#
#4400
1#
0$
#4420
0#
#4440
1#
1$
b1000 )
#4460
0#
#4480
1#
0$
#4500
0#
#4520
1#
1$
b1001 )
#4540
0#
#4560
1#
0$
#4580
0#
#4600
1#
1$
b1010 )
#4620
0#
#4640
1#
0$
#4660
0#
#4680
1#
1$
b1011 )
#4700
0#
#4720
1#
0$
#4740
0#
#4760
1#
1$
b1100 )
#4780
0#
#4800
1#
0$
#4820
0#
#4840
1#
1$
b1101 )
#4860
0#
#4880
1#
0$
#4900
0#
#4920
1#
1$
b1110 )
