Verilator_Tests/clk/top.v
module top (
    input clk_25mhz,
    output [3:0] led
);
    assign led[0] = clk_25mhz;
endmodule

Verilator_Tests/clk/wave.vcd
$version Generated by VerilatedVcd $end
$timescale 1ps $end
 $scope module TOP $end
  $var wire 1 # clk_25mhz $end
  $var wire 4 $ led [3:0] $end
  $scope module top $end
   $var wire 1 # clk_25mhz $end
   $var wire 4 $ led [3:0] $end
  $upscope $end
 $upscope $end
$enddefinitions $end


#0
1#
b0001 $
#20
0#
b0000 $
#40
1#
b0001 $
#60
0#
b0000 $
#80
1#
b0001 $
#100
0#
b0000 $
#120
1#
b0001 $
#140
0#
b0000 $
#160
1#
b0001 $
#180
0#
b0000 $
#200
1#
b0001 $
#220
0#
b0000 $
#240
1#
b0001 $
#260
0#
b0000 $
#280
1#
b0001 $
#300
0#
b0000 $
#320
1#
b0001 $
#340
0#
b0000 $
#360
1#
b0001 $
#380
0#
b0000 $
#400
1#
b0001 $
#420
0#
b0000 $
#440
1#
b0001 $
#460
0#
b0000 $
#480
1#
b0001 $
